setup.py
mandrill_webhooks/__init__.py
mandrill_webhooks/mandrill_webhooks.py
mandrill_webhooks.egg-info/PKG-INFO
mandrill_webhooks.egg-info/SOURCES.txt
mandrill_webhooks.egg-info/dependency_links.txt
mandrill_webhooks.egg-info/requires.txt
mandrill_webhooks.egg-info/top_level.txt