Metadata-Version: 1.0
Name: mandrill-webhooks
Version: 0.1.0
Summary: Flask Webhooks
Home-page: https://github.com/ecarreras/mandrill_webhooks
Author: ecarreras
Author-email: ecarreras@gmail.com
License: MIT
Platform: UNKNOWN
